seismolib/__init__.py
seismolib/display.py
seismolib/geo.py
seismolib/gk.py
seismolib/meca.py
seismolib/plots.py
seismolib/signal.py
seismolib/times.py
seismolib/traveltime.py
seismolib/utils.py
seismolib/vmodels.py
seismolib-25.8.2.dist-info/METADATA
seismolib-25.8.2.dist-info/WHEEL
seismolib-25.8.2.dist-info/licenses/LICENSE
seismolib-25.8.2.dist-info/RECORD
