Metadata-Version: 2.4
Name: seismolib
Version: 25.8.2
Summary: Small Python codes to help with data analysis in seismology.
Project-URL: Homepage, https://github.com/tktmyd/seismolib
Author-email: Takuto Maeda <tktmyd@hirosaki-u.ac.jp>
License-File: LICENSE
Classifier: License :: OSI Approved :: MIT License
Classifier: Operating System :: OS Independent
Classifier: Programming Language :: Python :: 3
Requires-Python: >=3.10
Requires-Dist: matplotlib>=3.8.0
Requires-Dist: numpy>=1.26.0
Requires-Dist: obspy>=1.4.1
Requires-Dist: pandas>=2.0.0
Requires-Dist: pygmt>=0.12.0
Requires-Dist: scipy>=1.12.0
